CHANGELOG.md
CITATION.cff
LICENSE.txt
MANIFEST.in
README.md
pyproject.toml
requirements.txt
setup.cfg
setup.py
pytorch_gleam/__about__.py
pytorch_gleam/__init__.py
pytorch_gleam.egg-info/PKG-INFO
pytorch_gleam.egg-info/SOURCES.txt
pytorch_gleam.egg-info/dependency_links.txt
pytorch_gleam.egg-info/entry_points.txt
pytorch_gleam.egg-info/not-zip-safe
pytorch_gleam.egg-info/requires.txt
pytorch_gleam.egg-info/top_level.txt
pytorch_gleam/callbacks/__init__.py
pytorch_gleam/callbacks/checkpoint.py
pytorch_gleam/callbacks/config.py
pytorch_gleam/callbacks/prediction.py
pytorch_gleam/callbacks/results.py
pytorch_gleam/data/__init__.py
pytorch_gleam/data/collators/__init__.py
pytorch_gleam/data/collators/base_collators.py
pytorch_gleam/data/collators/bert_pre.py
pytorch_gleam/data/collators/kbi.py
pytorch_gleam/data/collators/multi_class_frame.py
pytorch_gleam/data/collators/multi_class_frame_edge.py
pytorch_gleam/data/collators/multi_class_frame_edge_morality.py
pytorch_gleam/data/collators/multi_label.py
pytorch_gleam/data/collators/multi_sequence.py
pytorch_gleam/data/collators/nli_text.py
pytorch_gleam/data/collators/sequence_to_sequence.py
pytorch_gleam/data/datasets/__init__.py
pytorch_gleam/data/datasets/base_datasets.py
pytorch_gleam/data/datasets/bert_pretrain.py
pytorch_gleam/data/datasets/kbi_misinfo_stance.py
pytorch_gleam/data/datasets/misinfo_stance.py
pytorch_gleam/data/datasets/multi_class_frame.py
pytorch_gleam/data/datasets/multi_class_frame_edge.py
pytorch_gleam/data/datasets/multi_class_frame_edge_morality.py
pytorch_gleam/data/datasets/multi_class_frame_edge_morality_iter.py
pytorch_gleam/data/datasets/multi_class_misinfo_stance.py
pytorch_gleam/data/datasets/multi_label.py
pytorch_gleam/data/datasets/multi_turn_qa_frame.py
pytorch_gleam/data/datasets/nli_text_stance.py
pytorch_gleam/data/datasets/senticnet5.py
pytorch_gleam/data/datasets/senticnet5_raw.py
pytorch_gleam/data/datasets/unified_stance.py
pytorch_gleam/data/tokenizers/__init__.py
pytorch_gleam/ex/__init__.py
pytorch_gleam/ex/gleam.py
pytorch_gleam/ex/predict.py
pytorch_gleam/ex/test.py
pytorch_gleam/ex/train.py
pytorch_gleam/ex/validate.py
pytorch_gleam/exqueue/__init__.py
pytorch_gleam/exqueue/exbqueue.py
pytorch_gleam/exqueue/exqueue.py
