Metadata-Version: 2.1
Name: pytorch-gleam
Version: 0.6.2
Summary: Social Media NLP package for PyTorch & PyTorch Lightning.
Home-page: https://github.com/Supermaxman/pytorch-gleam
Author: Maxwell Weinzierl
Author-email: maxwell.weinzierl@utdallas.edu
License: Apache-2.0
Download-URL: https://github.com/Supermaxman/pytorch-gleam
Project-URL: Bug Tracker, https://github.com/Supermaxman/pytorch-gleam/issues
Project-URL: Source Code, https://github.com/Supermaxman/pytorch-gleam
Keywords: social media,twitter,pytorch,torch,pytorch_lightning,nlp,deep learning
Platform: UNKNOWN
Classifier: Environment :: Console
Classifier: Natural Language :: English
Classifier: Development Status :: 3 - Alpha
Classifier: Intended Audience :: Developers
Classifier: Topic :: Scientific/Engineering :: Artificial Intelligence
Classifier: Topic :: Scientific/Engineering :: Information Analysis
Classifier: License :: OSI Approved :: Apache Software License
Classifier: Operating System :: OS Independent
Classifier: Programming Language :: Python :: 3
Classifier: Programming Language :: Python :: 3.6
Classifier: Programming Language :: Python :: 3.7
Classifier: Programming Language :: Python :: 3.8
Classifier: Programming Language :: Python :: 3.9
Requires-Python: >=3.6
License-File: LICENSE.txt
